README.md
setup.py
django_oneskyapp/__init__.py
django_oneskyapp.egg-info/PKG-INFO
django_oneskyapp.egg-info/SOURCES.txt
django_oneskyapp.egg-info/dependency_links.txt
django_oneskyapp.egg-info/requires.txt
django_oneskyapp.egg-info/top_level.txt
django_oneskyapp/management/__init__.py
django_oneskyapp/management/commands/__init__.py
django_oneskyapp/management/commands/oneskyapp.py
testapp/__init__.py
testapp/manage.py
testapp/settings.py