Metadata-Version: 1.1
Name: django-oneskyapp
Version: 0.2
Summary: OneSkyApp translation service management commands for your django app
Home-page: http://github.com/pista329/django-oneskyapp
Author: Stefan Backor
Author-email: stefan@backor.sk
License: MIT
Platform: UNKNOWN
Classifier: Programming Language :: Python
Classifier: Programming Language :: Python :: 2.7
Classifier: Programming Language :: Python :: 3.3
Classifier: Programming Language :: Python :: 3.4
Classifier: Topic :: Software Development :: Libraries :: Python Modules
Classifier: Framework :: Django
Classifier: Environment :: Web Environment
Classifier: Operating System :: OS Independent
Classifier: Natural Language :: English
